sweetest/22.py
sweetest/33.py
sweetest/__init__.py
sweetest/autotest.py
sweetest/config.py
sweetest/data.py
sweetest/database.py
sweetest/elements.py
sweetest/globals.py
sweetest/injson.py
sweetest/junit.py
sweetest/locator.py
sweetest/log.py
sweetest/parse.py
sweetest/report.py
sweetest/send.py
sweetest/send_copy.py
sweetest/snapshot.py
sweetest/testcase.py
sweetest/testsuite.py
sweetest/utility.py
sweetest/windows.py
sweetest/keywords/__init__.py
sweetest/keywords/common.py
sweetest/keywords/files.py
sweetest/keywords/http.py
sweetest/keywords/mobile.py
sweetest/keywords/web.py
sweetest/keywords/windows.py
sweetest/lib/__init__.py
sweetest/lib/c.py
sweetest/lib/http_handle.py
sweetest/lib/u.py
ZXHT_AutoTest-1.0.0.dist-info/METADATA
ZXHT_AutoTest-1.0.0.dist-info/WHEEL
ZXHT_AutoTest-1.0.0.dist-info/top_level.txt
ZXHT_AutoTest-1.0.0.dist-info/RECORD
