Metadata-Version: 2.1
Name: ZXHT_AutoTest
Version: 1.0.0
Summary: ZXHT_AutoTest/sweetest
Author: TJF
Requires-Python: >=3.6
